topsis_vishwas_102317022/__init__.py
topsis_vishwas_102317022/topsis.py
topsis_vishwas_102317022-0.0.1.dist-info/licenses/LICENSE
topsis_vishwas_102317022-0.0.1.dist-info/METADATA
topsis_vishwas_102317022-0.0.1.dist-info/WHEEL
topsis_vishwas_102317022-0.0.1.dist-info/entry_points.txt
topsis_vishwas_102317022-0.0.1.dist-info/top_level.txt
topsis_vishwas_102317022-0.0.1.dist-info/RECORD
